pacoteaula/__init__.py
pacoteaula/modulo.py
pacoteaula-0.0.1.dist-info/LICENSE
pacoteaula-0.0.1.dist-info/METADATA
pacoteaula-0.0.1.dist-info/WHEEL
pacoteaula-0.0.1.dist-info/top_level.txt
pacoteaula-0.0.1.dist-info/RECORD
