Metadata-Version: 2.1
Name: pacoteaula
Version: 0.0.1
Summary: Pacote python para exibir número de 1 a 9
Home-page: https://github.com/marcos-de-sousa/pacotepypi
Author: Leonardo de Meiderios Bernardes
Author-email: leonardo22070053@aluno.cesupa.br
License: MIT License
Keywords: Pacote
Platform: UNKNOWN
License-File: LICENSE
Requires-Dist: numpy
